dino/__init__.py
dino/client.py
dino-0.0.6.dist-info/LICENSE
dino-0.0.6.dist-info/METADATA
dino-0.0.6.dist-info/WHEEL
dino-0.0.6.dist-info/top_level.txt
dino-0.0.6.dist-info/RECORD
