Metadata-Version: 2.1
Name: dino
Version: 0.0.6
Summary: A python API client for Dino monitoring service
Home-page: https://github.com/EnergieID/dino
Author: EnergieID
Author-email: jan@energieid.be
License: MIT
Keywords: dino data monitoring api
Platform: UNKNOWN
Classifier: Development Status :: 3 - Alpha
Classifier: Intended Audience :: Developers
Classifier: Topic :: Scientific/Engineering
Classifier: License :: OSI Approved :: MIT License
Classifier: Programming Language :: Python :: 3
Classifier: Programming Language :: Python :: 3.2
Classifier: Programming Language :: Python :: 3.3
Classifier: Programming Language :: Python :: 3.4
Classifier: Programming Language :: Python :: 3.5
Classifier: Programming Language :: Python :: 3.6
Requires-Dist: requests
Requires-Dist: pandas
